tablearn/__init__.py
tablearn-0.1.0.dist-info/WHEEL
tablearn-0.1.0.dist-info/METADATA
tablearn-0.1.0.dist-info/RECORD
