Metadata-Version: 2.1
Name: tablearn
Version: 0.1.0
Summary: tablearn: Learner for Tabular Data
Author: yajiez
Author-email: yajiez.me@gmail.com
Requires-Python: >=3.7,<4.0
Classifier: Programming Language :: Python :: 3
Classifier: Programming Language :: Python :: 3.7
Requires-Dist: catboost (>=0.20.0,<0.21.0)
Requires-Dist: lightgbm (>=2.3,<3.0)
Requires-Dist: numpy (>=1.17,<2.0)
Requires-Dist: pandas (>=0.25.3,<0.26.0)
Requires-Dist: pendulum (>=2.0,<3.0)
Requires-Dist: scikit-learn (>=0.21.3,<0.22.0)
Requires-Dist: seaborn (>=0.9.0,<0.10.0)
Requires-Dist: torch (>=1.3,<2.0)
Requires-Dist: torchvision (>=0.4.2,<0.5.0)
Requires-Dist: xgboost (>=0.90.0,<0.91.0)
